Metadata-Version: 2.1
Name: alibabacloud-nls-python-sdk
Version: 1.0.2
Summary: python sdk for nls
Home-page: https://github.com/..
Author: jiaqi.sjq
Author-email: jiaqi.sjq@alibaba-inc.com
License: Apache License 2.0
Keywords: nls,sdk
Classifier: Programming Language :: Python :: 3
Classifier: License :: OSI Approved :: Apache Software License
Classifier: Operating System :: OS Independent
License-File: LICENSE
Requires-Dist: oss2
Requires-Dist: aliyun-python-sdk-core>=2.13.3
Requires-Dist: matplotlib>=3.3.4
